securetkterminal/SerialConnectionDialog.py
securetkterminal/SerialKeyHandler.py
securetkterminal/TerminalSSH.py
securetkterminal/TerminalSerial.py
securetkterminal/__init__.py
securetkterminal/datastream.txt
securetkterminal/key_handler.py
securetkterminal/log_handler_ssh.py
securetkterminal/main_serial.py
securetkterminal/main_ssh.py
securetkterminal/ssh_handler.py
securetkterminal-0.2.0.dist-info/LICENSE
securetkterminal-0.2.0.dist-info/METADATA
securetkterminal-0.2.0.dist-info/WHEEL
securetkterminal-0.2.0.dist-info/entry_points.txt
securetkterminal-0.2.0.dist-info/top_level.txt
securetkterminal-0.2.0.dist-info/RECORD
