Metadata-Version: 2.1
Name: securetkterminal
Version: 0.2.0
Summary: A comprehensive terminal emulation application built with Python, Tkinter and sv-ttk, supporting serial communication and SSH connectivity with advanced features like window resizing, font adjustment, and terminal history management.
Home-page: https://github.com/scottpeterman/securetkterminal
Author: Scott Peterman
Author-email: scottpeterman@gmail.com
Classifier: Programming Language :: Python :: 3
Classifier: License :: OSI Approved :: MIT License
Classifier: Operating System :: OS Independent
Requires-Python: >=3.6
License-File: LICENSE
Requires-Dist: bcrypt >=4.1.2
Requires-Dist: cffi >=1.16.0
Requires-Dist: cryptography >=42.0.2
Requires-Dist: paramiko >=3.4.0
Requires-Dist: pillow >=10.2.0
Requires-Dist: pycparser >=2.21
Requires-Dist: PyNaCl >=1.5.0
Requires-Dist: pyserial >=3.5
Requires-Dist: pyte >=0.8.2
Requires-Dist: sv-ttk >=2.6.0
Requires-Dist: wcwidth >=0.2.13
